printer_zhanat/__init__.py
printer_zhanat/__main__.py
printer_zhanat/api.py
printer_zhanat/apps/__init__.py
printer_zhanat/apps/client/MyQRCode1.png
printer_zhanat/apps/client/__init__.py
printer_zhanat/apps/client/generate_qr_code.py
printer_zhanat/apps/client/usb_connection.py
printer_zhanat/apps/config/__init__.py
printer_zhanat/apps/config/settings.py
printer_zhanat/apps/fastapi_client/__init__.py
printer_zhanat/apps/fastapi_client/api_client.py
printer_zhanat/evdev_test.py
printer_zhanat/main.py
printer_zhanat/test_dict_class.py
printer_zhanat/uvicorn_client_api.py
printer_zhanat-0.1.0.dist-info/WHEEL
printer_zhanat-0.1.0.dist-info/METADATA
printer_zhanat-0.1.0.dist-info/RECORD
