Metadata-Version: 2.1
Name: printer-zhanat
Version: 0.1.0
Summary: 
Author: Zhanat
Author-email: janat.200066@gmail.com
Requires-Python: >=3.10,<4.0
Classifier: Programming Language :: Python :: 3
Classifier: Programming Language :: Python :: 3.10
Classifier: Programming Language :: Python :: 3.11
Requires-Dist: escpos (>=1.9,<2.0)
Requires-Dist: fastapi (>=0.103.1,<0.104.0)
Requires-Dist: pydantic (>=2.3.0,<3.0.0)
Requires-Dist: pydantic-settings (>=2.0.3,<3.0.0)
Requires-Dist: python-escpos[usb] (>=2.2.0,<3.0.0)
Requires-Dist: uvicorn (>=0.23.2,<0.24.0)
